jupyda.py
src/__init__.py
src/magic_jupyda.py
jupyda-0.0.7.dist-info/LICENSE
jupyda-0.0.7.dist-info/METADATA
jupyda-0.0.7.dist-info/WHEEL
jupyda-0.0.7.dist-info/top_level.txt
jupyda-0.0.7.dist-info/RECORD
